a_selenium_keys2coords/LICENSE
a_selenium_keys2coords/README.MD
a_selenium_keys2coords/__init__.py
a_selenium_keys2coords/requirements.txt
a_selenium_keys2coords/thirdparty.json
a_selenium_keys2coords-0.10.dist-info/LICENSE.rst
a_selenium_keys2coords-0.10.dist-info/METADATA
a_selenium_keys2coords-0.10.dist-info/WHEEL
a_selenium_keys2coords-0.10.dist-info/top_level.txt
a_selenium_keys2coords-0.10.dist-info/RECORD
